TimeSub/__init__.py
TimeSub/estimation.py
TimeSub/prediction.py
timesub-2.0.1.dist-info/METADATA
timesub-2.0.1.dist-info/WHEEL
timesub-2.0.1.dist-info/top_level.txt
timesub-2.0.1.dist-info/RECORD
