Metadata-Version: 2.4
Name: TimeSub
Version: 2.0.1
Summary: A Python package for survival analysis with competing risks
Home-page: https://github.com/sjtu1znj/TimeSub
Author: Nengjie Zhu
Author-email: sjtu_znj@sjtu.edu.cn
Keywords: survival analysis,competing risks,neural networks,hypothesis testing,time-to-event prediction
Platform: any
Requires-Dist: lifelines==0.30.0
Requires-Dist: numpy==2.2.5
Requires-Dist: scipy==1.15.2
Requires-Dist: torch==2.5.1
Dynamic: author
Dynamic: author-email
Dynamic: description
Dynamic: home-page
Dynamic: keywords
Dynamic: platform
Dynamic: requires-dist
Dynamic: summary
